berrynet/__init__.py
berrynet/dlmodelmgr.py
berrynet/utils.py
berrynet/bndyda/__init__.py
berrynet/bndyda/bnpipeline.py
berrynet/bndyda/launcher_berrynet.py
berrynet/bndyda/output_processor.py
berrynet/bndyda/pipeline.py
berrynet/bndyda/pipeline_restarter.py
berrynet/bndyda/warmup.py
berrynet/client/__init__.py
berrynet/client/camera.py
berrynet/client/dashboard.py
berrynet/client/data_collector.py
berrynet/client/data_collector_ui.py
berrynet/client/dyda_config_update.py
berrynet/client/fbdashboard.py
berrynet/client/gmail.py
berrynet/client/snapshot.py
berrynet/client/telegram_bot.py
berrynet/comm/__init__.py
berrynet/comm/payload.py
berrynet/engine/__init__.py
berrynet/engine/caffe_engine.py
berrynet/engine/darknet_engine.py
berrynet/engine/movidius.py
berrynet/engine/movidius_engine.py
berrynet/engine/openvino_engine.py
berrynet/engine/tensorflow_engine.py
berrynet/engine/tflite_engine.py
berrynet/engine/tfliteyolov4_engine.py
berrynet/service/__init__.py
berrynet/service/darknet_service.py
berrynet/service/dyda_config_update.py
berrynet/service/mockup_service.py
berrynet/service/movidius_service.py
berrynet/service/openvino_service.py
berrynet/service/tensorflow_service.py
berrynet/service/tflite_service.py
berrynet/service/tfliteyolov4_service.py
berrynet-3.10.1.dist-info/AUTHORS
berrynet-3.10.1.dist-info/LICENSE.txt
berrynet-3.10.1.dist-info/METADATA
berrynet-3.10.1.dist-info/WHEEL
berrynet-3.10.1.dist-info/entry_points.txt
berrynet-3.10.1.dist-info/top_level.txt
berrynet-3.10.1.dist-info/RECORD
