Metadata-Version: 2.1
Name: berrynet
Version: 3.10.1
Summary: Deep learning gateway on Raspberry Pi and other edge devices.
Home-page: https://github.com/DT42/BerryNet
Author: DT42 Inc.
Author-email: berrynet@dt42.io
License: GPLv3
Keywords: wheels
Platform: UNKNOWN
Classifier: Development Status :: 4 - Beta
Classifier: Intended Audience :: Science/Research
Classifier: Topic :: Scientific/Engineering :: Artificial Intelligence
Classifier: License :: OSI Approved :: GNU General Public License v3 (GPLv3)
Classifier: Programming Language :: Python :: 3
Classifier: Programming Language :: Python :: 3.4
Classifier: Programming Language :: Python :: 3.5
Classifier: Programming Language :: Python :: 3.6
Requires-Python: >=3
Requires-Dist: PyOpenGL
Requires-Dist: PyOpenGL-accelerate
Requires-Dist: logzero
Requires-Dist: paho-mqtt
